idelib/__init__.py
idelib/attributes.py
idelib/dataset.py
idelib/importer.py
idelib/matfile.py
idelib/multi_importer.py
idelib/parsers.py
idelib/transforms.py
idelib/unit_conversion.py
idelib/userdata.py
idelib/util.py
idelib/schemata/__init__.py
idelib/schemata/mide_ide.xml
idelib-3.2.10.dist-info/LICENSE
idelib-3.2.10.dist-info/METADATA
idelib-3.2.10.dist-info/WHEEL
idelib-3.2.10.dist-info/top_level.txt
idelib-3.2.10.dist-info/RECORD
