Metadata-Version: 2.1
Name: idelib
Version: 3.2.10
Summary: Python API for accessing IDE data recordings
Home-page: https://github.com/MideTechnology/idelib
Author: Mide Technology
Author-email: help@mide.com
License: MIT
Project-URL: Bug Tracker, https://github.com/MideTechnology/idelib/issues
Project-URL: Documentation, https://mide-technology-idelib.readthedocs-hosted.com/en/latest/
Project-URL: Source Code, https://github.com/MideTechnology/idelib
Keywords: ebml binary ide mide
Classifier: Development Status :: 5 - Production/Stable
Classifier: License :: OSI Approved :: MIT License
Classifier: Natural Language :: English
Classifier: Programming Language :: Python :: 3.8
Classifier: Programming Language :: Python :: 3.9
Classifier: Programming Language :: Python :: 3.10
Classifier: Programming Language :: Python :: 3.11
Classifier: Topic :: Scientific/Engineering
Requires-Python: >=3.5
License-File: LICENSE
Requires-Dist: numpy
Requires-Dist: ebmlite >=3.1.0
Provides-Extra: docs
Requires-Dist: numpy ; extra == 'docs'
Requires-Dist: ebmlite >=3.1.0 ; extra == 'docs'
Requires-Dist: sphinx >=5.0.2 ; extra == 'docs'
Requires-Dist: pydata-sphinx-theme ==0.7.2 ; extra == 'docs'
Requires-Dist: nbsphinx ; extra == 'docs'
Provides-Extra: example
Requires-Dist: numpy ; extra == 'example'
Requires-Dist: ebmlite >=3.1.0 ; extra == 'example'
Requires-Dist: matplotlib ; extra == 'example'
Provides-Extra: test
Requires-Dist: numpy ; extra == 'test'
Requires-Dist: ebmlite >=3.1.0 ; extra == 'test'
Requires-Dist: pytest >=4.6 ; extra == 'test'
Requires-Dist: pytest-xdist[psutil] ; extra == 'test'
Requires-Dist: mock ; extra == 'test'
Requires-Dist: pytest-cov ; extra == 'test'
Requires-Dist: sphinx >=5.0.2 ; extra == 'test'
Requires-Dist: setuptools ; extra == 'test'
Requires-Dist: scipy ; (python_version < "3.10") and extra == 'test'
